{
  "img": "http://www.legco.gov.hk/images/mem_1216/mc.jpg",
  "id": "mc",
  "name_ch": "毛孟靜",
  "constituency_ch": {
    "type": "地方選區",
    "area": "九龍西"
  },
  "educations_ch": [
    "大學新聞學士"
  ],
  "occupations_ch": [
    "傳媒工作者",
    "兼職講師"
  ],
  "parties_ch": [
    "公民黨"
  ],
  "email": "contact@msmo.hk",
  "homepage": "http://www.claudiamo.com",
  "name_en": "Claudia MO",
  "constituency_en": {
    "type": "Geographical Constituency",
    "area": "Kowloon West"
  },
  "educations_en": [
    "Bachelor of Journalism"
  ],
  "occupations_en": [
    "Media Freelancer",
    "Part-time Lecturer"
  ],
  "parties_en": [
    "Civic Party"
  ]
}